{
  "group": "declinera",
  "type": "minecraft:crafting_shaped",
  "pattern": [
    "012",
    "3 5"
  ],
  "key": {
    "0": {
      "item": "declinera:declinera_primary"
    },
    "1": {
      "item": "declinera:declinera_primary_core"
    },
    "2": {
      "item": "declinera:declinera_primary"
    },
    "3": {
      "item": "declinera:declinera_primary"
    },
    "5": {
      "item": "declinera:declinera_primary"
    }
  },
  "result": {
    "item": "declinera:declinera_primary_armorboots",
    "count": 1
  }
}